LICENSE
README.md
setup.py
safe_pip/__init__.py
safe_pip/main.py
safe_pip.egg-info/PKG-INFO
safe_pip.egg-info/SOURCES.txt
safe_pip.egg-info/dependency_links.txt
safe_pip.egg-info/entry_points.txt
safe_pip.egg-info/requires.txt
safe_pip.egg-info/top_level.txt