Metadata-Version: 2.1
Name: safe-pip
Version: 1.0.0
Summary: A safer pip that checks package health before installation.
Home-page: https://github.com/gkpln3/safe-pip
Author: Guy Kaplan
Author-email: gkpln3@gmail.com
License: UNKNOWN
Platform: UNKNOWN
Classifier: Programming Language :: Python :: 3
Classifier: License :: OSI Approved :: MIT License
License-File: LICENSE
